{
  "dateSydney": "2026-02-19",
  "lastUpdatedSydney": "2026-02-19 15:20",
  "locked": false,
  "quotes": [
    {
      "symbol": "CSL.AX",
      "percentDay": 0.85,
      "price": null,
      "prevClose": null,
      "timeEpoch": null
    },
    {
      "symbol": "BHP.AX",
      "percentDay": 2.25,
      "price": null,
      "prevClose": null,
      "timeEpoch": null
    },
    {
      "symbol": "WBC.AX",
      "percentDay": 2.65,
      "price": null,
      "prevClose": null,
      "timeEpoch": null
    },
    {
      "symbol": "WES.AX",
      "percentDay": -3.85,
      "price": null,
      "prevClose": null,
      "timeEpoch": null
    },
    {
      "symbol": "CBA.AX",
      "percentDay": -1.22,
      "price": null,
      "prevClose": null,
      "timeEpoch": null
    },
    {
      "symbol": "RIO.AX",
      "percentDay": 1.68,
      "price": null,
      "prevClose": null,
      "timeEpoch": null
    },
    {
      "symbol": "MQG.AX",
      "percentDay": 1.63,
      "price": null,
      "prevClose": null,
      "timeEpoch": null
    },
    {
      "symbol": "NAB.AX",
      "percentDay": 1.82,
      "price": null,
      "prevClose": null,
      "timeEpoch": null
    }
  ]
}